database/__init__.py
database/config.py
database/models.py
database/repositories/__init__.py
database/repositories/base.py
database/repositories/extracted_page.py
grabber/__init__.py
grabber/__main__.py
grabber/controllers/__init__.py
grabber/controllers/base.py
grabber/core/__init__.py
grabber/core/exc.py
grabber/core/settings.py
grabber/core/version.py
grabber/core/bot/__init__.py
grabber/core/bot/config.py
grabber/core/bot/core.py
grabber/core/bot/interactive_bot.py
grabber/core/extractor/__init__.py
grabber/core/extractor/base.py
grabber/core/extractor/constants.py
grabber/core/sources/__init__.py
grabber/core/sources/asianviralhub.py
grabber/core/sources/asiaontop.py
grabber/core/sources/buondua.py
grabber/core/sources/bypass.py
grabber/core/sources/celeb_cx.py
grabber/core/sources/chunmomo.py
grabber/core/sources/common.py
grabber/core/sources/cosxuxi.py
grabber/core/sources/ehentai.py
grabber/core/sources/eporner.py
grabber/core/sources/erome.py
grabber/core/sources/erome_tv.py
grabber/core/sources/erome_vip.py
grabber/core/sources/everia.py
grabber/core/sources/fapachi.py
grabber/core/sources/fapello.py
grabber/core/sources/fapello_pics.py
grabber/core/sources/fapello_ru.py
grabber/core/sources/fapello_su.py
grabber/core/sources/fapello_to.py
grabber/core/sources/fapexy.py
grabber/core/sources/fapeza.py
grabber/core/sources/fapodrop.py
grabber/core/sources/fapomania.py
grabber/core/sources/faponic.py
grabber/core/sources/fuligirl.py
grabber/core/sources/graph.py
grabber/core/sources/hentai_club.py
grabber/core/sources/hotgirl2024.py
grabber/core/sources/hotgirl_asia.py
grabber/core/sources/hotgirl_china.py
grabber/core/sources/hotleaks.py
grabber/core/sources/jrants.py
grabber/core/sources/kemono.py
grabber/core/sources/khd.py
grabber/core/sources/kup.py
grabber/core/sources/leakedzone.py
grabber/core/sources/leakgallery.py
grabber/core/sources/lewdweb.py
grabber/core/sources/lovecos.py
grabber/core/sources/masterfap.py
grabber/core/sources/misskon.py
grabberlib2-0.10.3.dist-info/METADATA
grabberlib2-0.10.3.dist-info/WHEEL
grabberlib2-0.10.3.dist-info/entry_points.txt
grabberlib2-0.10.3.dist-info/RECORD
