Metadata-Version: 2.4
Name: grabberlib2
Version: 0.10.3
Requires-Python: <4.0,>=3.10
Requires-Dist: ada-url>=1.15.3
Requires-Dist: aerich==0.7.2
Requires-Dist: aiogram==3.22.0
Requires-Dist: aiograph>=0.2
Requires-Dist: aiosqlite>=0.20.0
Requires-Dist: alive-progress==3.1.5
Requires-Dist: beautifulsoup4==4.12.3
Requires-Dist: boltons>=24.1.0
Requires-Dist: boto3==1.35.38
Requires-Dist: browser-cookie3>=0.20.1
Requires-Dist: casefy==0.1.7
Requires-Dist: cement==3.0.12
Requires-Dist: cloudscraper>=1.2.71
Requires-Dist: colorama==0.4.6
Requires-Dist: colorlog==6.8.2
Requires-Dist: crawlee[all,beautifulsoup,parsel,playwright]==0.6.9
Requires-Dist: defusedxml==0.7.1
Requires-Dist: environs==14.1.1
Requires-Dist: ftfy>=6.3.1
Requires-Dist: httpx[http2]==0.28.1
Requires-Dist: jinja2==3.1.3
Requires-Dist: lxml==5.2.1
Requires-Dist: nest-asyncio>=1.6.0
Requires-Dist: olefile==0.47
Requires-Dist: patool==2.1.1
Requires-Dist: pgcli>=4.1.0
Requires-Dist: pillow==10.3.0
Requires-Dist: pybypass==2.0.1
Requires-Dist: pydoll-python==2.9.0
Requires-Dist: python-telegram-bot[callback-data,job-queue,rate-limiter,webhooks]>=21.7
Requires-Dist: requests-html==0.10.0
Requires-Dist: requests==2.31.0
Requires-Dist: rich==13.7.1
Requires-Dist: selenium-stealth>=1.0.6
Requires-Dist: selenium==4.24.0
Requires-Dist: streamlit-extras==0.4.3
Requires-Dist: streamlit==1.35.0
Requires-Dist: telegraph==2.2.0
Requires-Dist: telethon>=1.39.0
Requires-Dist: tenacity==8.2.3
Requires-Dist: tortoise-orm[asyncpg,psycopg]>=0.22.1
Requires-Dist: tqdm==4.66.4
Requires-Dist: tweepy>=4.16.0
Requires-Dist: undetected-chromedriver>=3.5.5
Requires-Dist: unidecode>=1.3.8
Requires-Dist: unipath==1.1
Requires-Dist: url-parser>=3.0.3
Requires-Dist: webdriver-manager==4.0.2
Requires-Dist: you-get>=0.4.1730
Requires-Dist: yt-dlp>=2025.8.11
